cabin/EfficiencyScanNetwork.py
cabin/LossFunctions.py
cabin/OneToOneLinear.py
cabin/__init__.py
cabin-0.3.3.dist-info/METADATA
cabin-0.3.3.dist-info/WHEEL
cabin-0.3.3.dist-info/licenses/LICENSE
cabin-0.3.3.dist-info/RECORD
